openai_utils/__init__.py
openai_utilties-3.6.dist-info/METADATA
openai_utilties-3.6.dist-info/WHEEL
openai_utilties-3.6.dist-info/top_level.txt
openai_utilties-3.6.dist-info/RECORD
