Metadata-Version: 2.1
Name: openai-utilties
Version: 3.6
Summary: Some external utilities to facilitate OpenAI's Utilites
Home-page: https://github.com/SimplyYourAverageDev/openai_utils
Author: YourAverageDev
License: MIT
Keywords: openai,utilities
Classifier: Development Status :: 5 - Production/Stable
Classifier: Intended Audience :: Developers
Classifier: Programming Language :: Python :: 3.9
Classifier: Programming Language :: Python :: 3.10
Classifier: Programming Language :: Python :: 3.11
Classifier: Programming Language :: Python :: 3.12
Classifier: Operating System :: Unix
Classifier: Operating System :: MacOS :: MacOS X
Classifier: Operating System :: Microsoft :: Windows
Requires-Dist: openai >=1.2.3
